README.md
setup.cfg
setup.py
RubiksCube/__init__.py
RubiksCube/MagicCube/__init__.py
RubiksCube/MagicCube/code/__init__.py
RubiksCube/MagicCube/code/axes3d.py
RubiksCube/MagicCube/code/cube.py
RubiksCube/MagicCube/code/cube_interactive.py
RubiksCube/MagicCube/code/projection.py
RubiksCube/MagicCube/code/simple_cube.py
RubiksCube/envs/__init__.py
RubiksCube/envs/cube_env.py
gym_cube.egg-info/PKG-INFO
gym_cube.egg-info/SOURCES.txt
gym_cube.egg-info/dependency_links.txt
gym_cube.egg-info/requires.txt
gym_cube.egg-info/top_level.txt