Metadata-Version: 1.0
Name: gym-cube
Version: 1.0.5
Summary: Rubik's cube environment with OpenAI gym
Home-page: https://github.com/alseambusher/gym-cube
Author: alseambusher
Author-email: UNKNOWN
License: UNKNOWN
Platform: UNKNOWN
